sensingsp/__init__.py
sensingsp/config.py
sensingsp/constants.py
sensingsp/ai/__init__.py
sensingsp/ai/extras/ConwaysGameofLife.py
sensingsp/ai/extras/__init__.py
sensingsp/ai/radarML/GANWaveforms.py
sensingsp/ai/radarML/HandGestureMisoCNN.py
sensingsp/ai/radarML/HumanHealthMonitoringConvAE_BiLSTM.py
sensingsp/ai/radarML/SHARPWifiSensing.py
sensingsp/ai/radarML/__init__.py
sensingsp/camera/__init__.py
sensingsp/camera/utils.py
sensingsp/environment/__init__.py
sensingsp/environment/environment.py
sensingsp/environment/models.py
sensingsp/environment/scenarios.py
sensingsp/hardware/__init__.py
sensingsp/hardware/radar/DeviceUI.py
sensingsp/hardware/radar/TImmWave.py
sensingsp/hardware/radar/XeThru.py
sensingsp/hardware/radar/XethruUI.py
sensingsp/hardware/radar/__init__.py
sensingsp/integratedSensorSuite/__init__.py
sensingsp/integratedSensorSuite/integratedSensorSuite.py
sensingsp/lidar/__init__.py
sensingsp/lidar/utils.py
sensingsp/probe/__init__.py
sensingsp/probe/utils.py
sensingsp/radar/__init__.py
sensingsp/radar/collector/__init__.py
sensingsp/radar/fmcwWaveform/__init__.py
sensingsp/radar/radiator/__init__.py
sensingsp/radar/transmitter/__init__.py
sensingsp/radar/utils/__init__.py
sensingsp/radar/utils/apps.py
sensingsp/radar/utils/mimo copy.py
sensingsp/radar/utils/mimo.py
sensingsp/radar/utils/radarutils.py
sensingsp/radar/utils/rss.py
sensingsp/radar/utils/datasets/CarryObject.py
sensingsp/radar/utils/datasets/__init__.py
sensingsp/radar/waveforms/__init__.py
sensingsp/radar/waveforms/radarwaveforms.py
sensingsp/raytracing/BlenderGeometry.py
sensingsp/raytracing/RayTracingFunctions.py
sensingsp/raytracing/__init__.py
sensingsp/raytracing/raytracing.py
sensingsp/ris/__init__.py
sensingsp/ris/utils.py
sensingsp/sonar/__init__.py
sensingsp/utils/__init__.py
sensingsp/utils/blenderUI.py
sensingsp/utils/hub.py
sensingsp/utils/output2matlab.py
sensingsp/utils/predefines.py
sensingsp/utils/processingfunctions.py
sensingsp/utils/stochastics.py
sensingsp-1.5.10.dist-info/licenses/LICENSE
sensingsp-1.5.10.dist-info/METADATA
sensingsp-1.5.10.dist-info/WHEEL
sensingsp-1.5.10.dist-info/top_level.txt
sensingsp-1.5.10.dist-info/RECORD
