Metadata-Version: 2.4
Name: sensingsp
Version: 1.5.10
Summary: SensingSP™ is an open-source library designed for simulating electromagnetic sensing systems and implementing signal processing and machine learning algorithms.
Home-page: https://sensingsp.github.io/
Author: Moein Ahmadi
Author-email: moein.ahmadi@uni.lu, gmoein@gmail.com
License: MIT
Classifier: Development Status :: 3 - Alpha
Classifier: Intended Audience :: Science/Research
Classifier: Intended Audience :: Developers
Classifier: Intended Audience :: Information Technology
Classifier: Topic :: Scientific/Engineering :: Information Analysis
Classifier: Topic :: Scientific/Engineering :: Physics
Classifier: License :: OSI Approved :: MIT License
Classifier: Programming Language :: Python :: 3.10
Classifier: Operating System :: OS Independent
Requires-Python: >=3.10
License-File: LICENSE
Requires-Dist: numpy<2.0.0
Requires-Dist: bpy>=4.0.0
Requires-Dist: matplotlib>=3.5.0
Requires-Dist: opencv-python>=4.5.0
Requires-Dist: PyQt5>=5.15.0
Requires-Dist: scipy>=1.9.0
Requires-Dist: numba>=0.56.0
Requires-Dist: torch>=1.12.0
Requires-Dist: scikit-learn>=1.0.0
Requires-Dist: seaborn>=0.11.0
Requires-Dist: tensorboard>=2.9.0
Requires-Dist: torchviz>=0.0.2
Requires-Dist: torchsummary>=1.5.0
Requires-Dist: PyWavelets>=1.7.0
Requires-Dist: pyserial>=3.5
Provides-Extra: no-deps
Dynamic: author
Dynamic: author-email
Dynamic: classifier
Dynamic: description
Dynamic: description-content-type
Dynamic: home-page
Dynamic: license
Dynamic: license-file
Dynamic: provides-extra
Dynamic: requires-dist
Dynamic: requires-python
Dynamic: summary
